pilclock/__init__.py
pilclock/__main__.py
pilclock/identity.py
pilclock/pilclock.py
pilclock/runner.py
pilclock-0.1.0.dist-info/AUTHORS.rst
pilclock-0.1.0.dist-info/LICENSE
pilclock-0.1.0.dist-info/METADATA
pilclock-0.1.0.dist-info/WHEEL
pilclock-0.1.0.dist-info/top_level.txt
pilclock-0.1.0.dist-info/RECORD
