Metadata-Version: 2.1
Name: pilclock
Version: 0.1.0
Summary: PilClock - LED based Raspberry PI Clock
Home-page: https://github.com/nradulovic/pilclock
Author: Nenad Radulovic
Author-email: nenad.b.radulovic@gmail.com
License: GNU General Public License v3
Keywords: pilclock
Platform: UNKNOWN
Classifier: Development Status :: 2 - Pre-Alpha
Classifier: Intended Audience :: Developers
Classifier: License :: OSI Approved :: GNU General Public License v3 (GPLv3)
Classifier: Natural Language :: English
Classifier: Programming Language :: Python :: 3
Classifier: Programming Language :: Python :: 3.4
Classifier: Programming Language :: Python :: 3.5
Classifier: Programming Language :: Python :: 3.6
Classifier: Programming Language :: Python :: 3.7
